{
    "type": "Feature",
    "properties": {
        "adcode": 140302,
        "name": "城区",
        "center": [
            113.586513,
            37.860938
        ],
        "centroid": [
            113.597621,
            37.851697
        ],
        "childrenNum": 0,
        "level": "district",
        "parent": {
            "adcode": 140300
        },
        "subFeatureIndex": 0,
        "acroutes": [
            100000,
            140000,
            140300
        ]
    },
    "geometry": {
        "type": "MultiPolygon",
        "coordinates": [
            [
                [
                    [
                        113.567761,
                        37.875104
                    ],
                    [
                        113.572627,
                        37.871648
                    ],
                    [
                        113.576963,
                        37.869872
                    ],
                    [
                        113.584058,
                        37.870303
                    ],
                    [
                        113.591108,
                        37.867777
                    ],
                    [
                        113.602078,
                        37.861511
                    ],
                    [
                        113.608723,
                        37.857063
                    ],
                    [
                        113.615571,
                        37.855011
                    ],
                    [
                        113.620245,
                        37.849743
                    ],
                    [
                        113.623072,
                        37.848821
                    ],
                    [
                        113.625223,
                        37.849769
                    ],
                    [
                        113.625313,
                        37.852485
                    ],
                    [
                        113.627014,
                        37.853675
                    ],
                    [
                        113.635325,
                        37.85264
                    ],
                    [
                        113.645991,
                        37.85001
                    ],
                    [
                        113.650789,
                        37.849821
                    ],
                    [
                        113.65276,
                        37.848829
                    ],
                    [
                        113.652388,
                        37.846527
                    ],
                    [
                        113.648356,
                        37.844113
                    ],
                    [
                        113.638501,
                        37.843734
                    ],
                    [
                        113.63528,
                        37.843302
                    ],
                    [
                        113.632555,
                        37.838922
                    ],
                    [
                        113.625279,
                        37.838715
                    ],
                    [
                        113.621472,
                        37.837844
                    ],
                    [
                        113.618364,
                        37.838862
                    ],
                    [
                        113.606324,
                        37.844389
                    ],
                    [
                        113.601999,
                        37.846286
                    ],
                    [
                        113.595546,
                        37.847881
                    ],
                    [
                        113.592809,
                        37.848079
                    ],
                    [
                        113.591705,
                        37.845794
                    ],
                    [
                        113.593226,
                        37.842044
                    ],
                    [
                        113.599319,
                        37.839776
                    ],
                    [
                        113.598508,
                        37.837844
                    ],
                    [
                        113.595309,
                        37.837689
                    ],
                    [
                        113.587797,
                        37.838586
                    ],
                    [
                        113.581028,
                        37.838965
                    ],
                    [
                        113.573753,
                        37.833291
                    ],
                    [
                        113.567705,
                        37.833067
                    ],
                    [
                        113.566815,
                        37.833903
                    ],
                    [
                        113.570059,
                        37.835275
                    ],
                    [
                        113.571613,
                        37.837413
                    ],
                    [
                        113.572503,
                        37.841794
                    ],
                    [
                        113.572705,
                        37.847312
                    ],
                    [
                        113.567829,
                        37.850054
                    ],
                    [
                        113.561499,
                        37.855011
                    ],
                    [
                        113.560508,
                        37.855244
                    ],
                    [
                        113.562794,
                        37.857744
                    ],
                    [
                        113.568358,
                        37.860235
                    ],
                    [
                        113.569957,
                        37.863468
                    ],
                    [
                        113.57007,
                        37.867045
                    ],
                    [
                        113.567761,
                        37.875104
                    ]
                ]
            ]
        ]
    }
}