{
    "type": "Feature",
    "properties": {
        "adcode": 141081,
        "name": "侯马市",
        "center": [
            111.371272,
            35.620302
        ],
        "centroid": [
            111.363659,
            35.615536
        ],
        "childrenNum": 0,
        "level": "district",
        "parent": {
            "adcode": 141000
        },
        "subFeatureIndex": 15,
        "acroutes": [
            100000,
            140000,
            141000
        ]
    },
    "geometry": {
        "type": "MultiPolygon",
        "coordinates": [
            [
                [
                    [
                        111.377291,
                        35.70231
                    ],
                    [
                        111.381229,
                        35.701095
                    ],
                    [
                        111.38521,
                        35.70069
                    ],
                    [
                        111.397265,
                        35.697793
                    ],
                    [
                        111.402743,
                        35.697388
                    ],
                    [
                        111.409122,
                        35.695503
                    ],
                    [
                        111.415567,
                        35.692387
                    ],
                    [
                        111.415347,
                        35.68698
                    ],
                    [
                        111.417217,
                        35.683443
                    ],
                    [
                        111.428458,
                        35.679486
                    ],
                    [
                        111.438203,
                        35.681542
                    ],
                    [
                        111.448366,
                        35.684441
                    ],
                    [
                        111.44962,
                        35.682992
                    ],
                    [
                        111.448168,
                        35.677382
                    ],
                    [
                        111.444561,
                        35.670899
                    ],
                    [
                        111.443175,
                        35.659709
                    ],
                    [
                        111.445132,
                        35.645899
                    ],
                    [
                        111.447288,
                        35.638089
                    ],
                    [
                        111.453624,
                        35.626785
                    ],
                    [
                        111.459079,
                        35.613904
                    ],
                    [
                        111.458903,
                        35.606528
                    ],
                    [
                        111.457825,
                        35.60018
                    ],
                    [
                        111.456945,
                        35.587966
                    ],
                    [
                        111.454988,
                        35.578137
                    ],
                    [
                        111.448454,
                        35.568963
                    ],
                    [
                        111.44599,
                        35.563158
                    ],
                    [
                        111.442339,
                        35.562736
                    ],
                    [
                        111.436707,
                        35.563595
                    ],
                    [
                        111.423047,
                        35.559522
                    ],
                    [
                        111.419593,
                        35.561691
                    ],
                    [
                        111.412444,
                        35.564999
                    ],
                    [
                        111.4113,
                        35.567917
                    ],
                    [
                        111.41152,
                        35.571927
                    ],
                    [
                        111.410354,
                        35.572177
                    ],
                    [
                        111.407912,
                        35.569384
                    ],
                    [
                        111.404524,
                        35.567012
                    ],
                    [
                        111.391634,
                        35.562331
                    ],
                    [
                        111.38598,
                        35.561644
                    ],
                    [
                        111.380085,
                        35.561738
                    ],
                    [
                        111.377885,
                        35.56013
                    ],
                    [
                        111.375773,
                        35.555995
                    ],
                    [
                        111.366204,
                        35.553248
                    ],
                    [
                        111.361893,
                        35.551235
                    ],
                    [
                        111.357229,
                        35.555246
                    ],
                    [
                        111.351334,
                        35.555745
                    ],
                    [
                        111.348386,
                        35.555339
                    ],
                    [
                        111.339169,
                        35.55214
                    ],
                    [
                        111.336089,
                        35.548425
                    ],
                    [
                        111.333603,
                        35.543821
                    ],
                    [
                        111.327774,
                        35.540668
                    ],
                    [
                        111.320691,
                        35.537609
                    ],
                    [
                        111.314421,
                        35.535798
                    ],
                    [
                        111.307426,
                        35.534502
                    ],
                    [
                        111.302388,
                        35.536094
                    ],
                    [
                        111.296251,
                        35.536204
                    ],
                    [
                        111.286506,
                        35.544274
                    ],
                    [
                        111.278499,
                        35.550345
                    ],
                    [
                        111.273043,
                        35.555293
                    ],
                    [
                        111.271305,
                        35.558944
                    ],
                    [
                        111.275661,
                        35.565405
                    ],
                    [
                        111.280412,
                        35.56709
                    ],
                    [
                        111.283976,
                        35.571943
                    ],
                    [
                        111.28193,
                        35.575344
                    ],
                    [
                        111.273571,
                        35.584846
                    ],
                    [
                        111.269216,
                        35.592115
                    ],
                    [
                        111.26629,
                        35.598027
                    ],
                    [
                        111.265432,
                        35.611846
                    ],
                    [
                        111.267258,
                        35.616368
                    ],
                    [
                        111.26816,
                        35.629903
                    ],
                    [
                        111.273395,
                        35.633692
                    ],
                    [
                        111.275595,
                        35.633692
                    ],
                    [
                        111.28204,
                        35.631634
                    ],
                    [
                        111.285736,
                        35.628453
                    ],
                    [
                        111.290268,
                        35.629779
                    ],
                    [
                        111.292247,
                        35.635048
                    ],
                    [
                        111.291037,
                        35.637855
                    ],
                    [
                        111.288266,
                        35.639928
                    ],
                    [
                        111.289894,
                        35.641378
                    ],
                    [
                        111.298737,
                        35.645088
                    ],
                    [
                        111.301178,
                        35.646694
                    ],
                    [
                        111.302014,
                        35.650139
                    ],
                    [
                        111.298605,
                        35.655969
                    ],
                    [
                        111.296977,
                        35.659974
                    ],
                    [
                        111.293413,
                        35.664229
                    ],
                    [
                        111.291763,
                        35.669512
                    ],
                    [
                        111.293479,
                        35.671959
                    ],
                    [
                        111.295767,
                        35.672692
                    ],
                    [
                        111.301046,
                        35.672754
                    ],
                    [
                        111.304544,
                        35.673938
                    ],
                    [
                        111.306854,
                        35.675886
                    ],
                    [
                        111.313299,
                        35.677398
                    ],
                    [
                        111.321636,
                        35.677429
                    ],
                    [
                        111.326256,
                        35.675933
                    ],
                    [
                        111.347572,
                        35.670728
                    ],
                    [
                        111.357669,
                        35.670744
                    ],
                    [
                        111.365984,
                        35.676026
                    ],
                    [
                        111.374277,
                        35.700862
                    ],
                    [
                        111.377291,
                        35.70231
                    ]
                ]
            ]
        ]
    }
}